[
  {
    "id": "park_entrance",
    "name": "Park Entrance",
    "color": "#fbbf24",
    "footprint": [[1]],
    "buildCost": 5000,
    "buildWeeks": 1,
    "limit": 1,
    "edgeOnly": true
  },
  {
    "id": "path",
    "name": "Path",
    "color": "#d6d3d1",
    "footprint": [[1]],
    "buildCost": 100,
    "buildWeeks": 0,
    "limit": null,
    "mustBeAdjacentTo": ["path", "park_entrance"]
  },
  {
    "id": "bathroom",
    "name": "Bathroom",
    "color": "#7dd3fc",
    "footprint": [[1, 1], [1, 1]],
    "buildCost": 3500,
    "buildWeeks": 3,
    "limit": null
  },
  {
    "id": "statue",
    "name": "Statue",
    "color": "#cbd5e1",
    "footprint": [[1]],
    "buildCost": 500,
    "buildWeeks": 0,
    "limit": null
  },
  {
    "id": "garden",
    "name": "Garden",
    "color": "#86efac",
    "footprint": [[1, 1]],
    "buildCost": 1000,
    "buildWeeks": 0,
    "limit": null
  },
  {
    "id": "fountain",
    "name": "Fountain",
    "color": "#93c5fd",
    "footprint": [
      [0, 1, 0],
      [1, 1, 1],
      [0, 1, 0]
    ],
    "buildCost": 3000,
    "buildWeeks": 3,
    "limit": null
  },
  {
    "id": "staff_lounge",
    "name": "Staff Lounge",
    "color": "#fca5a5",
    "footprint": [[1, 1], [1, 1]],
    "buildCost": 2000,
    "buildWeeks": 3,
    "utilityCost": 50,
    "limit": null
  }
]
